[
    {
        "id": "10921",
        "path_to_svs": "10921.svs",
        "path_to_dzi": "10921.dzi",
        "probabilities": {
            "Cellular infiltration": 0.578,
            "Necrosis": 0.0,
            "Single cell necrosis": 0.002,
            "Hypertrophy": 1.42,
            "Change, eosinophilic": 0.008,
            "Ground glass appearance": 0.003,
            "Degeneration, hydropic": 0.002,
            "Deposit, glycogen": 0.0,
            "Fatty change": 2.651,
            "Proliferation, bile duct": 0.625,
            "Increased mitosis": 0.252,
            "Hematopoiesis, extramedullary": 0.018
        },
        "predictions": {
            "Cellular infiltration": false,
            "Necrosis": false,
            "Single cell necrosis": false,
            "Hypertrophy": false,
            "Change, eosinophilic": false,
            "Ground glass appearance": false,
            "Degeneration, hydropic": false,
            "Deposit, glycogen": false,
            "Fatty change": false,
            "Proliferation, bile duct": false,
            "Increased mitosis": true,
            "Hematopoiesis, extramedullary": false
        },
        "heatmaps": {
            "Cellular infiltration": "10921_cellular_infiltration_blockmap.png",
            "Necrosis": "10921_necrosis_blockmap.png",
            "Single cell necrosis": "10921_single_cell_necrosis_blockmap.png",
            "Hypertrophy": "10921_hypertrophy_blockmap.png",
            "Change, eosinophilic": "10921_eosinophilic_degeneration_blockmap.png",
            "Ground glass appearance": "10921_ground_glass_appearance_blockmap.png",
            "Degeneration, hydropic": "10921_hydropic_degeneration_blockmap.png",
            "Deposit, glycogen": "10921_glycogen_deposit_blockmap.png",
            "Fatty change": "10921_fatty_change_blockmap.png",
            "Proliferation, bile duct": "10921_bile_duct_proliferation_blockmap.png",
            "Increased mitosis": "10921_increased_mitosis_blockmap.png",
            "Hematopoiesis, extramedullary": "10921_extrameduallary_hematopoeisis_blockmap.png"
        },
        "enable_ai": false,
        "metadata": {
            "compound": "N/A",
            "dose": "N/A",
            "single/repeat": "N/A"
        }
    },
    {
        "id": "14012",
        "path_to_svs": "14012.svs",
        "path_to_dzi": "14012.dzi",
        "probabilities": {
            "Cellular infiltration": 0.2,
            "Necrosis": 0.028,
            "Single cell necrosis": 0.008,
            "Hypertrophy": 0.0,
            "Change, eosinophilic": 0.068,
            "Ground glass appearance": 0.001,
            "Degeneration, hydropic": 0.025,
            "Deposit, glycogen": 0.0,
            "Fatty change": 0.229,
            "Proliferation, bile duct": 0.032,
            "Increased mitosis": 0.002,
            "Hematopoiesis, extramedullary": 0.019
        },
        "predictions": {
            "Cellular infiltration": false,
            "Necrosis": true,
            "Single cell necrosis": false,
            "Hypertrophy": false,
            "Change, eosinophilic": false,
            "Ground glass appearance": false,
            "Degeneration, hydropic": false,
            "Deposit, glycogen": false,
            "Fatty change": false,
            "Proliferation, bile duct": false,
            "Increased mitosis": false,
            "Hematopoiesis, extramedullary": false
        },
        "heatmaps": {
            "Cellular infiltration": "14012_cellular_infiltration_blockmap.png",
            "Necrosis": "14012_necrosis_blockmap.png",
            "Single cell necrosis": "14012_single_cell_necrosis_blockmap.png",
            "Hypertrophy": "14012_hypertrophy_blockmap.png",
            "Change, eosinophilic": "14012_eosinophilic_degeneration_blockmap.png",
            "Ground glass appearance": "14012_ground_glass_appearance_blockmap.png",
            "Degeneration, hydropic": "14012_hydropic_degeneration_blockmap.png",
            "Deposit, glycogen": "14012_glycogen_deposit_blockmap.png",
            "Fatty change": "14012_fatty_change_blockmap.png",
            "Proliferation, bile duct": "14012_bile_duct_proliferation_blockmap.png",
            "Increased mitosis": "14012_increased_mitosis_blockmap.png",
            "Hematopoiesis, extramedullary": "14012_extrameduallary_hematopoeisis_blockmap.png"
        },
        "enable_ai": false,
        "metadata": {
            "compound": "N/A",
            "dose": "N/A",
            "single/repeat": "N/A"
        }
    },
    {
        "id": "14430",
        "path_to_svs": "14430.svs",
        "path_to_dzi": "14430.dzi",
        "probabilities": {
            "Cellular infiltration": 0.104,
            "Necrosis": 0.039,
            "Single cell necrosis": 0.005,
            "Hypertrophy": 0.0,
            "Change, eosinophilic": 0.056,
            "Ground glass appearance": 0.001,
            "Degeneration, hydropic": 0.026,
            "Deposit, glycogen": 0.0,
            "Fatty change": 0.089,
            "Proliferation, oval cell": 0.0,
            "Proliferation, bile duct": 0.0,
            "Increased mitosis": 0.001,
            "Hematopoiesis, extramedullary": 0.003
        },
        "labels": {
            "Cellular infiltration": 0,
            "Necrosis": 1,
            "Single cell necrosis": 0,
            "Hypertrophy": 0,
            "Change, eosinophilic": 0,
            "Ground glass appearance": 0,
            "Degeneration, hydropic": 0,
            "Deposit, glycogen": 0,
            "Fatty change": 0,
            "Proliferation, bile duct": 0,
            "Increased mitosis": 0,
            "Hematopoiesis, extramedullary": 0
        },
        "predictions": {
            "Cellular infiltration": false,
            "Necrosis": true,
            "Single cell necrosis": false,
            "Hypertrophy": false,
            "Change, eosinophilic": false,
            "Ground glass appearance": false,
            "Degeneration, hydropic": false,
            "Deposit, glycogen": false,
            "Fatty change": false,
            "Proliferation, bile duct": false,
            "Increased mitosis": false,
            "Hematopoiesis, extramedullary": false
        },
        "heatmaps": {
            "Cellular infiltration": "14430_cellular_infiltration_blockmap.png",
            "Necrosis": "14430_necrosis_blockmap.png",
            "Single cell necrosis": "14430_single_cell_necrosis_blockmap.png",
            "Hypertrophy": "14430_hypertrophy_blockmap.png",
            "Change, eosinophilic": "14430_eosinophilic_degeneration_blockmap.png",
            "Ground glass appearance": "14430_ground_glass_appearance_blockmap.png",
            "Degeneration, hydropic": "14430_hydropic_degeneration_blockmap.png",
            "Deposit, glycogen": "14430_glycogen_deposit_blockmap.png",
            "Fatty change": "14430_fatty_change_blockmap.png",
            "Proliferation, bile duct": "14430_bile_duct_proliferation_blockmap.png",
            "Increased mitosis": "14430_increased_mitosis_blockmap.png",
            "Hematopoiesis, extramedullary": "14430_extrameduallary_hematopoeisis_blockmap.png"
        },
        "enable_ai": false,
        "metadata": {
            "compound": "N/A",
            "dose": "N/A",
            "single/repeat": "N/A"
        }
    },
    {
        "id": "19714",
        "path_to_svs": "19714.svs",
        "path_to_dzi": "19714.dzi",
        "probabilities": {
            "Cellular infiltration": 0.028,
            "Necrosis": 0.0,
            "Single cell necrosis": 0.0,
            "Hypertrophy": 23.351,
            "Change, eosinophilic": 7.765,
            "Ground glass appearance": 5.97,
            "Degeneration, hydropic": 0.007,
            "Deposit, glycogen": 0.031,
            "Fatty change": 0.463,
            "Proliferation, bile duct": 0.0,
            "Increased mitosis": 0.0,
            "Hematopoiesis, extramedullary": 0.002
        },
        "labels": {
            "Cellular infiltration": 0,
            "Necrosis": 0,
            "Single cell necrosis": 0,
            "Hypertrophy": 1,
            "Change, eosinophilic": 1,
            "Ground glass appearance": 0,
            "Degeneration, hydropic": 0,
            "Deposit, glycogen": 0,
            "Fatty change": 1,
            "Proliferation, bile duct": 0,
            "Increased mitosis": 0,
            "Hematopoiesis, extramedullary": 0
        },
        "predictions": {
            "Cellular infiltration": false,
            "Necrosis": false,
            "Single cell necrosis": false,
            "Hypertrophy": true,
            "Change, eosinophilic": false,
            "Ground glass appearance": false,
            "Degeneration, hydropic": false,
            "Deposit, glycogen": false,
            "Fatty change": false,
            "Proliferation, bile duct": false,
            "Increased mitosis": false,
            "Hematopoiesis, extramedullary": false
        },
        "heatmaps": {
            "Cellular infiltration": "19714_cellular_infiltration_blockmap.png",
            "Necrosis": "19714_necrosis_blockmap.png",
            "Single cell necrosis": "19714_single_cell_necrosis_blockmap.png",
            "Hypertrophy": "19714_hypertrophy_blockmap.png",
            "Change, eosinophilic": "19714_eosinophilic_degeneration_blockmap.png",
            "Ground glass appearance": "19714_ground_glass_appearance_blockmap.png",
            "Degeneration, hydropic": "19714_hydropic_degeneration_blockmap.png",
            "Deposit, glycogen": "19714_glycogen_deposit_blockmap.png",
            "Fatty change": "19714_fatty_change_blockmap.png",
            "Proliferation, bile duct": "19714_bile_duct_proliferation_blockmap.png",
            "Increased mitosis": "19714_increased_mitosis_blockmap.png",
            "Hematopoiesis, extramedullary": "19714_extrameduallary_hematopoeisis_blockmap.png"
        },
        "enable_ai": false,
        "metadata": {
            "compound": "N/A",
            "dose": "N/A",
            "single/repeat": "N/A"
        }
    },
    {
        "id": "30270",
        "path_to_svs": "30270.svs",
        "path_to_dzi": "30270.dzi",
        "probabilities": {
            "Cellular infiltration": 10.6,
            "Necrosis": 0.143,
            "Single cell necrosis": 0.0,
            "Hypertrophy": 0.0,
            "Change, eosinophilic": 35.012,
            "Ground glass appearance": 23.259,
            "Degeneration, hydropic": 17.299,
            "Deposit, glycogen": 0.0,
            "Fatty change": 0.164,
            "Proliferation, bile duct": 0.056,
            "Increased mitosis": 0.0,
            "Hematopoiesis, extramedullary": 0.002
        },
        "labels": {
            "Cellular infiltration": 1,
            "Necrosis": 1,
            "Single cell necrosis": 0,
            "Hypertrophy": 0,
            "Change, eosinophilic": 1,
            "Ground glass appearance": 0,
            "Degeneration, hydropic": 1,
            "Deposit, glycogen": 0,
            "Fatty change": 0,
            "Proliferation, bile duct": 0,
            "Increased mitosis": 0,
            "Hematopoiesis, extramedullary": 0
        },
        "predictions": {
            "Cellular infiltration": true,
            "Necrosis": true,
            "Single cell necrosis": false,
            "Hypertrophy": false,
            "Change, eosinophilic": true,
            "Ground glass appearance": true,
            "Degeneration, hydropic": true,
            "Deposit, glycogen": false,
            "Fatty change": false,
            "Proliferation, bile duct": false,
            "Increased mitosis": false,
            "Hematopoiesis, extramedullary": false
        },
        "heatmaps": {
            "Cellular infiltration": "30270_cellular_infiltration_blockmap.png",
            "Necrosis": "30270_necrosis_blockmap.png",
            "Single cell necrosis": "30270_single_cell_necrosis_blockmap.png",
            "Hypertrophy": "30270_hypertrophy_blockmap.png",
            "Change, eosinophilic": "30270_eosinophilic_degeneration_blockmap.png",
            "Ground glass appearance": "30270_ground_glass_appearance_blockmap.png",
            "Degeneration, hydropic": "30270_hydropic_degeneration_blockmap.png",
            "Deposit, glycogen": "30270_glycogen_deposit_blockmap.png",
            "Fatty change": "30270_fatty_change_blockmap.png",
            "Proliferation, bile duct": "30270_bile_duct_proliferation_blockmap.png",
            "Increased mitosis": "30270_increased_mitosis_blockmap.png",
            "Hematopoiesis, extramedullary": "30270_extrameduallary_hematopoeisis_blockmap.png"
        },
        "enable_ai": false,
        "metadata": {
            "compound": "N/A",
            "dose": "N/A",
            "single/repeat": "N/A"
        }
    },
    {
        "id": "30272",
        "path_to_svs": "30272.svs",
        "path_to_dzi": "30272.dzi",
        "probabilities": {
            "Cellular infiltration": 7.848,
            "Necrosis": 0.012,
            "Single cell necrosis": 0.003,
            "Hypertrophy": 0.0,
            "Change, eosinophilic": 42.136,
            "Ground glass appearance": 35.127,
            "Degeneration, hydropic": 13.265,
            "Deposit, glycogen": 0.0,
            "Fatty change": 0.112,
            "Proliferation, bile duct": 0.022,
            "Increased mitosis": 0.0,
            "Hematopoiesis, extramedullary": 0.008
        },
        "labels": {
            "Cellular infiltration": 1,
            "Necrosis": 1,
            "Single cell necrosis": 0,
            "Hypertrophy": 0,
            "Change, eosinophilic": 1,
            "Ground glass appearance": 0,
            "Degeneration, hydropic": 1,
            "Deposit, glycogen": 0,
            "Fatty change": 0,
            "Proliferation, bile duct": 0,
            "Increased mitosis": 0,
            "Hematopoiesis, extramedullary": 0
        },
        "predictions": {
            "Cellular infiltration": true,
            "Necrosis": true,
            "Single cell necrosis": false,
            "Hypertrophy": false,
            "Change, eosinophilic": true,
            "Ground glass appearance": true,
            "Degeneration, hydropic": true,
            "Deposit, glycogen": false,
            "Fatty change": false,
            "Proliferation, bile duct": false,
            "Increased mitosis": false,
            "Hematopoiesis, extramedullary": false
        },
        "heatmaps": {
            "Cellular infiltration": "30272_cellular_infiltration_blockmap.png",
            "Necrosis": "30272_necrosis_blockmap.png",
            "Single cell necrosis": "30272_single_cell_necrosis_blockmap.png",
            "Hypertrophy": "30272_hypertrophy_blockmap.png",
            "Change, eosinophilic": "30272_eosinophilic_degeneration_blockmap.png",
            "Ground glass appearance": "30272_ground_glass_appearance_blockmap.png",
            "Degeneration, hydropic": "30272_hydropic_degeneration_blockmap.png",
            "Deposit, glycogen": "30272_glycogen_deposit_blockmap.png",
            "Fatty change": "30272_fatty_change_blockmap.png",
            "Proliferation, bile duct": "30272_bile_duct_proliferation_blockmap.png",
            "Increased mitosis": "30272_increased_mitosis_blockmap.png",
            "Hematopoiesis, extramedullary": "30272_extrameduallary_hematopoeisis_blockmap.png"
        },
        "enable_ai": false,
        "metadata": {
            "compound": "N/A",
            "dose": "N/A",
            "single/repeat": "N/A"
        }
    },
    {
        "id": "46078",
        "path_to_svs": "46078.svs",
        "path_to_dzi": "46078.dzi",
        "probabilities": {
            "Cellular infiltration": 0.759,
            "Necrosis": 0.0,
            "Single cell necrosis": 1.88,
            "Hypertrophy": 0.964,
            "Change, eosinophilic": 3.818,
            "Ground glass appearance": 0.289,
            "Degeneration, hydropic": 0.0,
            "Deposit, glycogen": 0.0,
            "Fatty change": 6.319,
            "Proliferation, bile duct": 0.089,
            "Increased mitosis": 0.002,
            "Hematopoiesis, extramedullary": 0.018
        },
        "labels": {
            "Cellular infiltration": 1,
            "Necrosis": 0,
            "Single cell necrosis": 1,
            "Hypertrophy": 0,
            "Change, eosinophilic": 1,
            "Ground glass appearance": 0,
            "Degeneration, hydropic": 0,
            "Deposit, glycogen": 0,
            "Fatty change": 0,
            "Proliferation, bile duct": 0,
            "Increased mitosis": 0,
            "Hematopoiesis, extramedullary": 0
        },
        "predictions": {
            "Cellular infiltration": false,
            "Necrosis": false,
            "Single cell necrosis": true,
            "Hypertrophy": false,
            "Change, eosinophilic": false,
            "Ground glass appearance": false,
            "Degeneration, hydropic": false,
            "Deposit, glycogen": false,
            "Fatty change": false,
            "Proliferation, bile duct": false,
            "Increased mitosis": false,
            "Hematopoiesis, extramedullary": false
        },
        "heatmaps": {
            "Cellular infiltration": "46078_cellular_infiltration_blockmap.png",
            "Necrosis": "46078_necrosis_blockmap.png",
            "Single cell necrosis": "46078_single_cell_necrosis_blockmap.png",
            "Hypertrophy": "46078_hypertrophy_blockmap.png",
            "Change, eosinophilic": "46078_eosinophilic_degeneration_blockmap.png",
            "Ground glass appearance": "46078_ground_glass_appearance_blockmap.png",
            "Degeneration, hydropic": "46078_hydropic_degeneration_blockmap.png",
            "Deposit, glycogen": "46078_glycogen_deposit_blockmap.png",
            "Fatty change": "46078_fatty_change_blockmap.png",
            "Proliferation, bile duct": "46078_bile_duct_proliferation_blockmap.png",
            "Increased mitosis": "46078_increased_mitosis_blockmap.png",
            "Hematopoiesis, extramedullary": "46078_extrameduallary_hematopoeisis_blockmap.png"
        },
        "enable_ai": false,
        "metadata": {
            "compound": "N/A",
            "dose": "N/A",
            "single/repeat": "N/A"
        }
    },
    {
        "id": "46360",
        "path_to_svs": "46360.svs",
        "path_to_dzi": "46360.dzi",
        "probabilities": {
            "Cellular infiltration": 0.142,
            "Necrosis": 0.0,
            "Single cell necrosis": 4.835,
            "Hypertrophy": 5.777,
            "Change, eosinophilic": 30.003,
            "Ground glass appearance": 1.206,
            "Degeneration, hydropic": 0.0,
            "Deposit, glycogen": 0.0,
            "Fatty change": 25.182,
            "Proliferation, bile duct": 0.01,
            "Increased mitosis": 0.013,
            "Hematopoiesis, extramedullary": 0.007
        },
        "labels": {
            "Cellular infiltration": 0,
            "Necrosis": 0,
            "Single cell necrosis": 1,
            "Hypertrophy": 0,
            "Change, eosinophilic": 0,
            "Ground glass appearance": 0,
            "Degeneration, hydropic": 0,
            "Deposit, glycogen": 0,
            "Fatty change": 0,
            "Proliferation, bile duct": 0,
            "Increased mitosis": 1,
            "Hematopoiesis, extramedullary": 0
        },
        "predictions": {
            "Cellular infiltration": false,
            "Necrosis": false,
            "Single cell necrosis": true,
            "Hypertrophy": false,
            "Change, eosinophilic": true,
            "Ground glass appearance": false,
            "Degeneration, hydropic": false,
            "Deposit, glycogen": false,
            "Fatty change": true,
            "Proliferation, bile duct": false,
            "Increased mitosis": false,
            "Hematopoiesis, extramedullary": false
        },
        "heatmaps": {
            "Cellular infiltration": "46360_cellular_infiltration_blockmap.png",
            "Necrosis": "46360_necrosis_blockmap.png",
            "Single cell necrosis": "46360_single_cell_necrosis_blockmap.png",
            "Hypertrophy": "46360_hypertrophy_blockmap.png",
            "Change, eosinophilic": "46360_eosinophilic_degeneration_blockmap.png",
            "Ground glass appearance": "46360_ground_glass_appearance_blockmap.png",
            "Degeneration, hydropic": "46360_hydropic_degeneration_blockmap.png",
            "Deposit, glycogen": "46360_glycogen_deposit_blockmap.png",
            "Fatty change": "46360_fatty_change_blockmap.png",
            "Proliferation, bile duct": "46360_bile_duct_proliferation_blockmap.png",
            "Increased mitosis": "46360_increased_mitosis_blockmap.png",
            "Hematopoiesis, extramedullary": "46360_extrameduallary_hematopoeisis_blockmap.png"
        },
        "enable_ai": false,
        "metadata": {
            "compound": "N/A",
            "dose": "N/A",
            "single/repeat": "N/A"
        }
    },
    {
        "id": "48472",
        "path_to_svs": "48472.svs",
        "path_to_dzi": "48472.dzi",
        "probabilities": {
            "Cellular infiltration": 0.036,
            "Necrosis": 0.0,
            "Single cell necrosis": 0.001,
            "Hypertrophy": 0.002,
            "Change, eosinophilic": 0.0,
            "Ground glass appearance": 0.0,
            "Degeneration, hydropic": 0.005,
            "Deposit, glycogen": 0.176,
            "Fatty change": 0.024,
            "Proliferation, oval cell": 0.0,
            "Proliferation, bile duct": 0.0,
            "Increased mitosis": 0.0,
            "Hematopoiesis, extramedullary": 0.013
        },
        "labels": {
            "Cellular infiltration": 0,
            "Necrosis": 0,
            "Single cell necrosis": 0,
            "Hypertrophy": 0,
            "Change, eosinophilic": 0,
            "Ground glass appearance": 0,
            "Degeneration, hydropic": 0,
            "Deposit, glycogen": 0,
            "Fatty change": 0,
            "Proliferation, bile duct": 0,
            "Increased mitosis": 0,
            "Hematopoiesis, extramedullary": 0
        },
        "predictions": {
            "Cellular infiltration": false,
            "Necrosis": false,
            "Single cell necrosis": false,
            "Hypertrophy": false,
            "Change, eosinophilic": false,
            "Ground glass appearance": false,
            "Degeneration, hydropic": false,
            "Deposit, glycogen": false,
            "Fatty change": false,
            "Proliferation, bile duct": false,
            "Increased mitosis": false,
            "Hematopoiesis, extramedullary": false
        },
        "heatmaps": {
            "Cellular infiltration": "48472_cellular_infiltration_blockmap.png",
            "Necrosis": "48472_necrosis_blockmap.png",
            "Single cell necrosis": "48472_single_cell_necrosis_blockmap.png",
            "Hypertrophy": "48472_hypertrophy_blockmap.png",
            "Change, eosinophilic": "48472_eosinophilic_degeneration_blockmap.png",
            "Ground glass appearance": "48472_ground_glass_appearance_blockmap.png",
            "Degeneration, hydropic": "48472_hydropic_degeneration_blockmap.png",
            "Deposit, glycogen": "48472_glycogen_deposit_blockmap.png",
            "Fatty change": "48472_fatty_change_blockmap.png",
            "Proliferation, bile duct": "48472_bile_duct_proliferation_blockmap.png",
            "Increased mitosis": "48472_increased_mitosis_blockmap.png",
            "Hematopoiesis, extramedullary": "48472_extrameduallary_hematopoeisis_blockmap.png"
        },
        "enable_ai": false,
        "metadata": {
            "compound": "N/A",
            "dose": "N/A",
            "single/repeat": "N/A"
        }
    }
]